spreadsnake/__init__.py
spreadsnake/google.py
spreadsnake/xlsx.py
spreadsnake-1.0a1.dist-info/LICENSE
spreadsnake-1.0a1.dist-info/METADATA
spreadsnake-1.0a1.dist-info/WHEEL
spreadsnake-1.0a1.dist-info/top_level.txt
spreadsnake-1.0a1.dist-info/RECORD
