Metadata-Version: 2.1
Name: spreadsnake
Version: 1.0a1
Summary: A python spreadsheet api
Home-page: https://github.com/RandomKiddo/spreadsnake
Author: RandomKiddo
Author-email: nghugare2@outlook.com
License: MIT
Download-URL: https://github.com/RandomKiddo/spreadsnake/archive/1.0a1.tar.gz
Keywords: PYTHON,SPREADSHEETS,API
Platform: UNKNOWN
Classifier: Development Status :: 3 - Alpha
Classifier: Intended Audience :: Developers
Classifier: Topic :: Software Development :: Build Tools
Classifier: License :: OSI Approved :: MIT License
Classifier: Programming Language :: Python :: 3.8
